{
	"backtraceGraph" : 
	{
		"commands" : 
		[
			"install"
		],
		"files" : 
		[
			"PFF/vendor/glfw/CMakeLists.txt"
		],
		"nodes" : 
		[
			{
				"file" : 0
			},
			{
				"command" : 0,
				"file" : 0,
				"line" : 150,
				"parent" : 0
			},
			{
				"command" : 0,
				"file" : 0,
				"line" : 153,
				"parent" : 0
			},
			{
				"command" : 0,
				"file" : 0,
				"line" : 157,
				"parent" : 0
			},
			{
				"command" : 0,
				"file" : 0,
				"line" : 160,
				"parent" : 0
			}
		]
	},
	"installers" : 
	[
		{
			"backtrace" : 1,
			"component" : "Unspecified",
			"destination" : "include",
			"paths" : 
			[
				"PFF/vendor/glfw/include/GLFW"
			],
			"type" : "directory"
		},
		{
			"backtrace" : 2,
			"component" : "Unspecified",
			"destination" : "lib/cmake/glfw3",
			"paths" : 
			[
				"out/build/x64-Debug/PFF/vendor/glfw/src/glfw3Config.cmake",
				"out/build/x64-Debug/PFF/vendor/glfw/src/glfw3ConfigVersion.cmake"
			],
			"type" : "file"
		},
		{
			"backtrace" : 3,
			"component" : "Unspecified",
			"destination" : "lib/cmake/glfw3",
			"exportName" : "glfwTargets",
			"exportTargets" : 
			[
				{
					"id" : "glfw::@3178b7fcc859b22e01ba",
					"index" : 3
				}
			],
			"paths" : 
			[
				"PFF/vendor/glfw/CMakeFiles/Export/f367bd07922f2ecfc14cf5547f1f7c4e/glfw3Targets.cmake"
			],
			"type" : "export"
		},
		{
			"backtrace" : 4,
			"component" : "Unspecified",
			"destination" : "lib/pkgconfig",
			"paths" : 
			[
				"out/build/x64-Debug/PFF/vendor/glfw/src/glfw3.pc"
			],
			"type" : "file"
		}
	],
	"paths" : 
	{
		"build" : "PFF/vendor/glfw",
		"source" : "PFF/vendor/glfw"
	}
}
